lammps_interface/BTW.py
lammps_interface/CIFIO.py
lammps_interface/Dubbeldam.py
lammps_interface/ForceFields.py
lammps_interface/InputHandler.py
lammps_interface/MOFFF.py
lammps_interface/Molecules.py
lammps_interface/__init__.py
lammps_interface/atomic.py
lammps_interface/ccdc.py
lammps_interface/create_cluster.py
lammps_interface/create_cluster_v2.py
lammps_interface/dreiding.py
lammps_interface/gas_models.py
lammps_interface/generic_raspa.py
lammps_interface/lammps_main.py
lammps_interface/lammps_potentials.py
lammps_interface/mof_sbus.py
lammps_interface/structure_data.py
lammps_interface/uff.py
lammps_interface/uff4mof.py
lammps_interface/uff_nonbonded.py
lammps_interface/water_models.py
lammps_interface-0.1.2.data/scripts/lammps-interface
lammps_interface-0.1.2.dist-info/LICENSE
lammps_interface-0.1.2.dist-info/METADATA
lammps_interface-0.1.2.dist-info/WHEEL
lammps_interface-0.1.2.dist-info/top_level.txt
lammps_interface-0.1.2.dist-info/RECORD
