Metadata-Version: 2.1
Name: lammps-interface
Version: 0.1.2
Summary: Automatic generation of LAMMPS input files for molecular dynamics simulations of MOFs
Home-page: https://github.com/peteboyd/lammps_interface
Author: Peter Boyd, Mohamad Moosavi, Matthew Witman
License: MIT
Platform: UNKNOWN
Requires-Dist: numpy
Requires-Dist: scipy
Requires-Dist: networkx (>=2.4)
Requires-Dist: matplotlib (<3.1)
Provides-Extra: docs
Requires-Dist: sphinx (<3,>=2) ; extra == 'docs'
Requires-Dist: sphinx-rtd-theme (<1,>=0.4) ; extra == 'docs'
